nuxai/__init__.py
nuxai-0.2.dist-info/METADATA
nuxai-0.2.dist-info/WHEEL
nuxai-0.2.dist-info/top_level.txt
nuxai-0.2.dist-info/RECORD
